ElasticEmailClient.py
ElasticEmailWebApiClient-1.0.9.dist-info/License.txt
ElasticEmailWebApiClient-1.0.9.dist-info/METADATA
ElasticEmailWebApiClient-1.0.9.dist-info/WHEEL
ElasticEmailWebApiClient-1.0.9.dist-info/top_level.txt
ElasticEmailWebApiClient-1.0.9.dist-info/RECORD
