Metadata-Version: 2.1
Name: ElasticEmailWebApiClient
Version: 1.0.9
Summary: Easily send emails with Elastic Email using Web API Python Client https://elasticemail.com/
Home-page: https://github.com/ElasticEmail/ElasticEmail.WebApiClient-python
Author: ElasticEmail Dev Team
Author-email: support@elasticemail.com
License: MIT
Keywords: elastic email elasticemail web api transactional
Platform: UNKNOWN
Classifier: Development Status :: 4 - Beta
Classifier: Intended Audience :: Developers
Classifier: Topic :: Software Development :: Build Tools
Classifier: License :: OSI Approved :: MIT License
Classifier: Programming Language :: Python :: 2
Classifier: Programming Language :: Python :: 2.7
Classifier: Programming Language :: Python :: 3
Classifier: Programming Language :: Python :: 3.3
Classifier: Programming Language :: Python :: 3.4
Classifier: Programming Language :: Python :: 3.5
